{
    "name": "Anonymous Black",
    "symbol": "A_Black",
    "type": "ERC20_WALLET",
    "website": "http://localhost:3000/websites/test-dummy-sites?sitename=AnonymousBlack",
    "description": "This is the description for site AnonymousBlack",
    "status": "test",
    "address": "0x0000000000000000000000000000000000000071",
    "block-scanners": [
        {
            "blockchain": "BASE",
            "explorer": "https://basescan.org/address/NA"
        },
        {
            "blockchain": "ETHEREUM",
            "url": "https://etherscan.io/address/0x0000000000000000000000000000000000000071"
        },
        {
            "blockchain": "POLYGON",
            "url": "https://polygonscan.com/address/NA"
        },
        {
            "blockchain": "SEPOLIA",
            "url": "https://sepolia.etherscan.io/address/NA"
        },
        {
            "blockchain": "HARDHAT",
            "url": "NA"
        }
    ],
    "tags": [
        "stablecoin"
    ]
}
